hpfeeds/__init__.py
hpfeeds/client.py
hpfeeds/exceptions.py
hpfeeds/protocol.py
hpfeeds/asyncio/__init__.py
hpfeeds/asyncio/client.py
hpfeeds/asyncio/protocol.py
hpfeeds/blocking/__init__.py
hpfeeds/blocking/protocol.py
hpfeeds/blocking/queue.py
hpfeeds/blocking/reactor.py
hpfeeds/blocking/session.py
hpfeeds/broker/__init__.py
hpfeeds/broker/connection.py
hpfeeds/broker/prometheus.py
hpfeeds/broker/server.py
hpfeeds/broker/auth/__init__.py
hpfeeds/broker/auth/env.py
hpfeeds/broker/auth/memory.py
hpfeeds/broker/auth/sqlite.py
hpfeeds/scripts/__init__.py
hpfeeds/scripts/broker.py
hpfeeds/scripts/cli.py
hpfeeds/tests/__init__.py
hpfeeds/tests/fakebroker.py
hpfeeds/tests/test_asyncio_client.py
hpfeeds/tests/test_asyncio_protocol.py
hpfeeds/tests/test_blocking_protocol.py
hpfeeds/tests/test_blocking_queue.py
hpfeeds/tests/test_blocking_session.py
hpfeeds/tests/test_broker_auth_env.py
hpfeeds/tests/test_broker_auth_sqlite.py
hpfeeds/tests/test_broker_connection.py
hpfeeds/tests/test_broker_prometheus.py
hpfeeds/tests/test_client_integration.py
hpfeeds/tests/test_client_integration_py2.py
hpfeeds/tests/test_protocol.py
hpfeeds/tests/test_twisted_factory.py
hpfeeds/tests/test_twisted_protocol.py
hpfeeds/tests/test_twisted_service.py
hpfeeds/tests/test_twisted_service_py2.py
hpfeeds/tests/testcert.crt
hpfeeds/tests/testcert.key
hpfeeds/tests/utils.py
hpfeeds/twisted/__init__.py
hpfeeds/twisted/factory.py
hpfeeds/twisted/protocol.py
hpfeeds/twisted/service.py
hpfeeds3-0.9.7.dist-info/METADATA
hpfeeds3-0.9.7.dist-info/RECORD
hpfeeds3-0.9.7.dist-info/WHEEL
hpfeeds3-0.9.7.dist-info/entry_points.txt
hpfeeds3-0.9.7.dist-info/top_level.txt
