Metadata-Version: 2.1
Name: hpfeeds3
Version: 0.9.7
Summary: Python implementation of the honeypot feeds broker
Home-page: https://github.com/Jc2k/hpfeeds
Author: John Carr
Author-email: john.carr@unrouted.co.uk
License: GPL
Platform: UNKNOWN
